PyVisualizer/CommonUtilities.py
PyVisualizer/Visualizer.py
PyVisualizer-1.0.9.dist-info/LICENSE
PyVisualizer-1.0.9.dist-info/METADATA
PyVisualizer-1.0.9.dist-info/WHEEL
PyVisualizer-1.0.9.dist-info/entry_points.txt
PyVisualizer-1.0.9.dist-info/top_level.txt
PyVisualizer-1.0.9.dist-info/RECORD
