Metadata-Version: 2.1
Name: PyVisualizer
Version: 1.0.9
Summary: A simple static visualizer(I can make it dynamic though :)).
Home-page: https://github.com/vishalkashyap95/PyVisualizer_Task2.git
Author: Vishal Kashyap
Author-email: vkashyap569@gmail.com
License: MIT
Platform: UNKNOWN
Classifier: License :: OSI Approved :: MIT License
Classifier: Programming Language :: Python :: 3.6
Classifier: Programming Language :: Python :: 3.7
Classifier: Programming Language :: Python :: 3.8
Requires-Dist: gspread
Requires-Dist: pandas
Requires-Dist: requests
Requires-Dist: matplotlib
Requires-Dist: seaborn
